shplotmissing/__init__.py
shplotmissing-0.3.dist-info/METADATA
shplotmissing-0.3.dist-info/WHEEL
shplotmissing-0.3.dist-info/top_level.txt
shplotmissing-0.3.dist-info/RECORD
