Metadata-Version: 2.1
Name: shplotmissing
Version: 0.3
Summary: SHAWPACK NLP processing package
Home-page: https://github.com/AbdelrahmanShahrour/shplotmissing
Author: AbdelrahmanShahrour
License: UNKNOWN
Keywords: Stucterd Data,AI,DS,Shahrour,Pandas,Missing Value
Platform: UNKNOWN
Classifier: Programming Language :: Python :: 3
Classifier: License :: OSI Approved :: MIT License
Classifier: Operating System :: OS Independent
Requires-Dist: Pillow (==9.3.0)
Requires-Dist: contourpy (==1.0.6)
Requires-Dist: cycler (==0.11.0)
Requires-Dist: fonttools (==4.38.0)
Requires-Dist: kiwisolver (==1.4.4)
Requires-Dist: matplotlib (==3.6.2)
Requires-Dist: missingno (==0.5.1)
Requires-Dist: numpy (==1.23.5)
Requires-Dist: packaging (==21.3)
Requires-Dist: pandas (==1.5.2)
Requires-Dist: pyparsing (==3.0.9)
Requires-Dist: python-dateutil (==2.8.2)
Requires-Dist: pytz (==2022.6)
Requires-Dist: scipy (==1.9.3)
Requires-Dist: seaborn (==0.12.1)
Requires-Dist: six (==1.16.0)
